{
  "coord": {
    "lon": 139.6917,
    "lat": 35.6895
  },
  "weather": [
    {
      "id": 501,
      "main": "Rain",
      "description": "moderate rain",
      "icon": "10n"
    }
  ],
  "base": "stations",
  "main": {
    "temp": 23.12,
    "feels_like": 23.52,
    "temp_min": 22.53,
    "temp_max": 23.8,
    "pressure": 1013,
    "humidity": 78,
    "sea_level": 1013,
    "grnd_level": 1011
  },
  "visibility": 10000,
  "wind": {
    "speed": 0.89,
    "deg": 133,
    "gust": 3.58
  },
  "rain": {
    "1h": 1.15
  },
  "clouds": {
    "all": 100
  },
  "dt": 1782296744,
  "sys": {
    "type": 2,
    "id": 268395,
    "country": "JP",
    "sunrise": 1782242776,
    "sunset": 1782295242
  },
  "timezone": 32400,
  "id": 1850144,
  "name": "Tokyo",
  "cod": 200,
  "_last_updated_utc": "2026-06-24T10:38:17.691Z"
}