{
  "coord": {
    "lon": 139.6917,
    "lat": 35.6895
  },
  "weather": [
    {
      "id": 800,
      "main": "Clear",
      "description": "clear sky",
      "icon": "01n"
    }
  ],
  "base": "stations",
  "main": {
    "temp": 24.87,
    "feels_like": 25.55,
    "temp_min": 23.12,
    "temp_max": 25.36,
    "pressure": 1012,
    "humidity": 82,
    "sea_level": 1012,
    "grnd_level": 1010
  },
  "visibility": 10000,
  "wind": {
    "speed": 2.01,
    "deg": 141,
    "gust": 2.55
  },
  "clouds": {
    "all": 7
  },
  "dt": 1782827100,
  "sys": {
    "type": 2,
    "id": 268395,
    "country": "JP",
    "sunrise": 1782761294,
    "sunset": 1782813664
  },
  "timezone": 32400,
  "id": 1850144,
  "name": "Tokyo",
  "cod": 200,
  "_last_updated_utc": "2026-06-30T13:50:26.811Z"
}