{
  "coord": {
    "lon": 139.6917,
    "lat": 35.6895
  },
  "weather": [
    {
      "id": 803,
      "main": "Clouds",
      "description": "broken clouds",
      "icon": "04d"
    }
  ],
  "base": "stations",
  "main": {
    "temp": 17.69,
    "feels_like": 17.73,
    "temp_min": 14.58,
    "temp_max": 18.79,
    "pressure": 1021,
    "humidity": 85,
    "sea_level": 1021,
    "grnd_level": 1019
  },
  "visibility": 10000,
  "wind": {
    "speed": 3.6,
    "deg": 180
  },
  "clouds": {
    "all": 75
  },
  "dt": 1778445270,
  "sys": {
    "type": 2,
    "id": 268395,
    "country": "JP",
    "sunrise": 1778442002,
    "sunset": 1778492117
  },
  "timezone": 32400,
  "id": 1850144,
  "name": "Tokyo",
  "cod": 200,
  "_last_updated_utc": "2026-05-10T20:35:36.479Z"
}