{
  "coord": {
    "lon": 139.6917,
    "lat": 35.6895
  },
  "weather": [
    {
      "id": 803,
      "main": "Clouds",
      "description": "broken clouds",
      "icon": "04d"
    }
  ],
  "base": "stations",
  "main": {
    "temp": 18.66,
    "feels_like": 18.41,
    "temp_min": 17.66,
    "temp_max": 19.35,
    "pressure": 1008,
    "humidity": 70,
    "sea_level": 1008,
    "grnd_level": 1006
  },
  "visibility": 10000,
  "wind": {
    "speed": 8.75,
    "deg": 310,
    "gust": 14.92
  },
  "clouds": {
    "all": 75
  },
  "dt": 1776734338,
  "sys": {
    "type": 2,
    "id": 268395,
    "country": "JP",
    "sunrise": 1776715284,
    "sunset": 1776763098
  },
  "timezone": 32400,
  "id": 1850144,
  "name": "Tokyo",
  "cod": 200,
  "_last_updated_utc": "2026-04-21T01:19:28.440Z"
}